[
  {
    "name": "mid",
    "value": "agqOLwALAAEdtDlmvumJXBiW58jQ",
    "domain": ".instagram.com",
    "path": "/",
    "expires": 1813636654.19814,
    "size": 31,
    "httpOnly": true,
    "secure": true,
    "session": false,
    "sameSite": "None",
    "priority": "Medium",
    "sourceScheme": "Secure",
    "sameParty": false
  },
  {
    "name": "datr",
    "value": "L44KakNiWq5OLJewyMMXVQaq",
    "domain": ".instagram.com",
    "path": "/",
    "expires": 1813636654.197976,
    "size": 28,
    "httpOnly": true,
    "secure": true,
    "session": false,
    "sameSite": "None",
    "priority": "Medium",
    "sourceScheme": "Secure",
    "sameParty": false
  },
  {
    "name": "csrftoken",
    "value": "jp1tgfDGwsoIXcHFOH7Qt1",
    "domain": ".instagram.com",
    "path": "/",
    "expires": 1813636676.445114,
    "size": 31,
    "httpOnly": false,
    "secure": true,
    "session": false,
    "priority": "Medium",
    "sourceScheme": "Secure",
    "sameParty": false
  },
  {
    "name": "ig_did",
    "value": "23C7D74C-02E3-4F3D-8FDB-962882603778",
    "domain": ".instagram.com",
    "path": "/",
    "expires": 1810612654.198065,
    "size": 42,
    "httpOnly": true,
    "secure": true,
    "session": false,
    "sameSite": "None",
    "priority": "Medium",
    "sourceScheme": "Secure",
    "sameParty": false
  },
  {
    "name": "dpr",
    "value": "1.0000000298023224",
    "domain": ".instagram.com",
    "path": "/",
    "expires": 1779681476,
    "size": 21,
    "httpOnly": false,
    "secure": true,
    "session": false,
    "sameSite": "None",
    "priority": "Medium",
    "sourceScheme": "Secure",
    "sameParty": false
  },
  {
    "name": "wd",
    "value": "800x600",
    "domain": ".instagram.com",
    "path": "/",
    "expires": 1779681476,
    "size": 9,
    "httpOnly": false,
    "secure": true,
    "session": false,
    "sameSite": "Lax",
    "priority": "Medium",
    "sourceScheme": "Secure",
    "sameParty": false
  },
  {
    "name": "ds_user_id",
    "value": "65803904683",
    "domain": ".instagram.com",
    "path": "/",
    "expires": 1786852676.445206,
    "size": 21,
    "httpOnly": false,
    "secure": true,
    "session": false,
    "sameSite": "None",
    "priority": "Medium",
    "sourceScheme": "Secure",
    "sameParty": false
  },
  {
    "name": "rur",
    "value": "\"HIL\\05465803904683\\0541810612677:01fec871d660819d1cd2f772c2e1e7582a99c6c84b2e29784f956356ad9fa9ed351d635f\"",
    "domain": ".instagram.com",
    "path": "/",
    "expires": -1,
    "size": 110,
    "httpOnly": true,
    "secure": true,
    "session": true,
    "sameSite": "Lax",
    "priority": "Medium",
    "sourceScheme": "Secure",
    "sameParty": false
  },
  {
    "name": "sessionid",
    "value": "65803904683%3AAKZQA53YUMpK4I%3A21%3AAYjB6_zh2PlLaWunpvtPGHGka_KKLAe22h697l6kgA",
    "domain": ".instagram.com",
    "path": "/",
    "expires": 1810612674.710459,
    "size": 87,
    "httpOnly": true,
    "secure": true,
    "session": false,
    "sameSite": "None",
    "priority": "Medium",
    "sourceScheme": "Secure",
    "sameParty": false
  }
]